apache/__init__.py
apache/airflow/__init__.py
apache/airflow/providers/__init__.py
apache/airflow/providers/clickhouse/__init__.py
apache/airflow/providers/clickhouse/hooks/ClickhouseHook.py
apache/airflow/providers/clickhouse/hooks/__init__.py
apache/airflow/providers/clickhouse/operators/ClickhouseOperator.py
apache/airflow/providers/clickhouse/operators/__init__.py
airflow_providers_clickhouse-0.0.1.dist-info/LICENSE
airflow_providers_clickhouse-0.0.1.dist-info/METADATA
airflow_providers_clickhouse-0.0.1.dist-info/WHEEL
airflow_providers_clickhouse-0.0.1.dist-info/entry_points.txt
airflow_providers_clickhouse-0.0.1.dist-info/top_level.txt
airflow_providers_clickhouse-0.0.1.dist-info/RECORD
