Metadata-Version: 2.1
Name: airflow-providers-clickhouse
Version: 0.0.1
Summary: Apache Airflow providers for Yandex Clickhouse Database
Home-page: https://github.com/klimenkoIv/apache-airflow-providers-clickhouse
Author: Ivan Klimenko
Author-email: klimenko.iv@gmail.com
License: Apache License 2.0
Project-URL: Bug Tracker, https://github.com/klimenkoIv/apache-airflow-providers-clickhouse/issues
Keywords: clickhouse,airflow,providers,database,ClickhouseHook,ClickhouseOperator
Platform: UNKNOWN
Classifier: Programming Language :: Python :: 3
Classifier: Operating System :: OS Independent
Requires-Python: >=3.6
License-File: LICENSE
Requires-Dist: apache-airflow (>=2.0)
Requires-Dist: clickhouse-driver (>=0.2.1)
Requires-Dist: pandas (>=1.3.2)
